aeroai_mistral/.DS_Store
aeroai_mistral/__init__.py
aeroai_mistral/ai/__init__.py
aeroai_mistral/py.typed
aeroai_mistral-0.0.4.dist-info/WHEEL
aeroai_mistral-0.0.4.dist-info/METADATA
aeroai_mistral-0.0.4.dist-info/RECORD
