Metadata-Version: 2.3
Name: aeroai-mistral
Version: 0.0.4
Summary: Mistral AI integration for AeroAI
Keywords: ai,mistral,llm,aeroai
Author: Florian Peschke
Author-email: Florian Peschke <florian.peschke@hyand.com>
Classifier: Development Status :: 3 - Alpha
Classifier: Intended Audience :: Developers
Classifier: License :: OSI Approved :: MIT License
Classifier: Programming Language :: Python :: 3
Classifier: Programming Language :: Python :: 3.13
Classifier: Topic :: Scientific/Engineering :: Artificial Intelligence
Classifier: Typing :: Typed
Requires-Dist: aeroai>=0.0.1
Requires-Python: >=3.13
Project-URL: Homepage, https://github.com/florianpeschke/aeroai
Project-URL: Issues, https://github.com/florianpeschke/aeroai/issues
Project-URL: Repository, https://github.com/florianpeschke/aeroai
